pazer/__init__.py
pazer-0.0.3.dev1.dist-info/LICENSE
pazer-0.0.3.dev1.dist-info/METADATA
pazer-0.0.3.dev1.dist-info/WHEEL
pazer-0.0.3.dev1.dist-info/top_level.txt
pazer-0.0.3.dev1.dist-info/RECORD
